odoo/addons/connector_importer/README.rst
odoo/addons/connector_importer/__init__.py
odoo/addons/connector_importer/__manifest__.py
odoo/addons/connector_importer/events.py
odoo/addons/connector_importer/log.py
odoo/addons/connector_importer/menuitems.xml
odoo/addons/connector_importer/components/__init__.py
odoo/addons/connector_importer/components/automapper.py
odoo/addons/connector_importer/components/base.py
odoo/addons/connector_importer/components/importer.py
odoo/addons/connector_importer/components/importer_csv_std.py
odoo/addons/connector_importer/components/mapper.py
odoo/addons/connector_importer/components/odoorecord.py
odoo/addons/connector_importer/components/odoorecord_csv_std.py
odoo/addons/connector_importer/components/tracker.py
odoo/addons/connector_importer/controllers/__init__.py
odoo/addons/connector_importer/controllers/main.py
odoo/addons/connector_importer/data/ir_cron.xml
odoo/addons/connector_importer/models/__init__.py
odoo/addons/connector_importer/models/backend.py
odoo/addons/connector_importer/models/cron_mixin.py
odoo/addons/connector_importer/models/import_type.py
odoo/addons/connector_importer/models/job_mixin.py
odoo/addons/connector_importer/models/record.py
odoo/addons/connector_importer/models/recordset.py
odoo/addons/connector_importer/models/reporter.py
odoo/addons/connector_importer/models/sources/__init__.py
odoo/addons/connector_importer/models/sources/source_csv.py
odoo/addons/connector_importer/models/sources/source_mixin.py
odoo/addons/connector_importer/readme/CONTRIBUTORS.rst
odoo/addons/connector_importer/readme/DESCRIPTION.rst
odoo/addons/connector_importer/readme/ROADMAP.rst
odoo/addons/connector_importer/security/ir.model.access.csv
odoo/addons/connector_importer/security/security.xml
odoo/addons/connector_importer/static/description/icon.png
odoo/addons/connector_importer/static/description/index.html
odoo/addons/connector_importer/tests/__init__.py
odoo/addons/connector_importer/tests/common.py
odoo12_addon_connector_importer-12.0.1.4.0.dist-info/METADATA
odoo12_addon_connector_importer-12.0.1.4.0.dist-info/WHEEL
odoo12_addon_connector_importer-12.0.1.4.0.dist-info/top_level.txt
odoo12_addon_connector_importer-12.0.1.4.0.dist-info/RECORD
