Metadata-Version: 2.1
Name: odoo12-addon-connector-importer
Version: 12.0.1.4.0
Summary: This module takes care of import sessions.
Home-page: https://github.com/OCA/connector-interfaces
Author: Camptocamp, Odoo Community Association (OCA)
Author-email: support@odoo-community.org
License: AGPL-3
Platform: UNKNOWN
Classifier: Programming Language :: Python
Classifier: Framework :: Odoo
Classifier: License :: OSI Approved :: GNU Affero General Public License v3
Requires-Python: >=3.5
Requires-Dist: chardet
Requires-Dist: odoo12-addon-connector
Requires-Dist: odoo12-addon-queue-job
Requires-Dist: odoo (<12.1dev,>=12.0a)
